README.md
setup.py
soundsgood/__init__.py
soundsgood.egg-info/PKG-INFO
soundsgood.egg-info/SOURCES.txt
soundsgood.egg-info/dependency_links.txt
soundsgood.egg-info/top_level.txt