Metadata-Version: 1.0
Name: soundsgood
Version: 0.0.1
Summary: Cos I don't think https://docs.python.org/3/tutorial/modules.html#packages is at all sound...
Home-page: https://github.com/alvations/soundsgood
Author: UNKNOWN
Author-email: UNKNOWN
License: UNKNOWN
Platform: UNKNOWN
